pysyt/__init__.py
pysyt/syt.py
pysyt-0.1.0.dist-info/LICENSE
pysyt-0.1.0.dist-info/METADATA
pysyt-0.1.0.dist-info/WHEEL
pysyt-0.1.0.dist-info/RECORD
