Metadata-Version: 2.1
Name: pysyt
Version: 0.1.0
Summary: Standard Young tableaux
Home-page: https://github.com/stla/pysyt
License: GPL-3.0-only
Keywords: combinatorics
Author: Stéphane Laurent
Author-email: laurent_step@outlook.fr
Requires-Python: >=3.10,<4.0
Classifier: License :: OSI Approved :: GNU General Public License v3 (GPLv3)
Classifier: Programming Language :: Python :: 3
Classifier: Programming Language :: Python :: 3.10
Classifier: Programming Language :: Python :: 3.11
Classifier: Programming Language :: Python :: 3.12
Provides-Extra: docs
Requires-Dist: sphinx (>=7.2.0,<8.0.0) ; extra == "docs"
Requires-Dist: sphinx-rtd-theme (>=1.3.0,<2.0.0) ; extra == "docs"
Requires-Dist: sphinxcontrib-napoleon (>=0.7,<0.8) ; extra == "docs"
Requires-Dist: sphinxcontrib-restbuilder (>=0.3,<0.4) ; extra == "docs"
Project-URL: Documentation, https://pysyt.readthedocs.io/en/latest/
